CHANGES.txt
CONTRIBUTORS.txt
README.txt
setup.py
src/buildout/__init__.py
src/buildout.eggtractor.egg-info/PKG-INFO
src/buildout.eggtractor.egg-info/SOURCES.txt
src/buildout.eggtractor.egg-info/dependency_links.txt
src/buildout.eggtractor.egg-info/entry_points.txt
src/buildout.eggtractor.egg-info/namespace_packages.txt
src/buildout.eggtractor.egg-info/not-zip-safe
src/buildout.eggtractor.egg-info/requires.txt
src/buildout.eggtractor.egg-info/top_level.txt
src/buildout/eggtractor/__init__.py
src/buildout/eggtractor/tests.py
src/buildout/eggtractor/tractor.py
src/buildout/eggtractor/tractor.txt