Metadata-Version: 1.0
Name: buildout.eggtractor
Version: 0.6
Summary: Auto generates zcml slugs, buildout:egg and buildout:develop entries.
Home-page: http://svn.plone.org/svn/collective/buildout/buildout.eggtractor
Author: Mustapha Benali
Author-email: mustapha@headnet.dk
License: GPL
Keywords: buildout extension egg tractor
Platform: UNKNOWN
Classifier: Framework :: Buildout
Classifier: Intended Audience :: Developers
Classifier: Topic :: Software Development :: Build Tools
Classifier: Topic :: Software Development :: Libraries :: Python Modules
